mcp_calendar/__init__.py
mcp_calendar/server.py
mcp_calendar_python-0.3.4.dist-info/METADATA
mcp_calendar_python-0.3.4.dist-info/WHEEL
mcp_calendar_python-0.3.4.dist-info/entry_points.txt
mcp_calendar_python-0.3.4.dist-info/top_level.txt
mcp_calendar_python-0.3.4.dist-info/RECORD
