Metadata-Version: 2.4
Name: mcp-calendar-python
Version: 0.3.4
Summary: MCP server for Google Calendar integration
Author-email: Jaemin You <2dois2be@gmail.com>
License: MIT
Project-URL: Homepage, https://github.com/tobedoit/gCalendar-mcp-python
Project-URL: Bug Tracker, https://github.com/tobedoit/gCalendar-mcp-python/issues
Project-URL: Source Code, https://github.com/tobedoit/gCalendar-mcp-python
Classifier: License :: OSI Approved :: MIT License
Classifier: Programming Language :: Python :: 3
Classifier: Programming Language :: Python :: 3.13
Classifier: Operating System :: OS Independent
Requires-Python: >=3.13
Requires-Dist: mcp[cli]>=1.20.0
Requires-Dist: python-dotenv>=1.2.1
Requires-Dist: google-api-python-client>=2.186.0
Requires-Dist: google-auth>=2.42.1
Requires-Dist: google-auth-oauthlib>=1.2.2
